duplicate_image_finder/__init__.py
duplicate_image_finder/duplicate_finder.py
duplicate_image_finder/template/bootstrap-theme.min.css
duplicate_image_finder/template/bootstrap.min.css
duplicate_image_finder/template/bootstrap.min.js
duplicate_image_finder/template/index.html
duplicate_image_finder/template/jquery-2.1.4.min.js
duplicate_image_finder-0.2.10.dist-info/entry_points.txt
duplicate_image_finder-0.2.10.dist-info/LICENSE
duplicate_image_finder-0.2.10.dist-info/WHEEL
duplicate_image_finder-0.2.10.dist-info/METADATA
duplicate_image_finder-0.2.10.dist-info/RECORD
