Metadata-Version: 2.1
Name: duplicate-image-finder
Version: 0.2.10
Summary: duplicate image finder helps you find duplicate or similar images as well as delete them.
Home-page: https://github.com/LordAmit/duplicate_image_finder
Keywords: image,similar image,duplicate image,imagehash
Author: Amit
Author-email: lordamit@gmail.com
Requires-Python: >=3.9,<3.10
Classifier: Programming Language :: Python :: 3
Classifier: Programming Language :: Python :: 3.9
Requires-Dist: Flask (>=2.1.2,<3.0.0)
Requires-Dist: Flask-Cors (>=3.0.10,<4.0.0)
Requires-Dist: ImageHash (>=4.2.1,<5.0.0)
Requires-Dist: Jinja2 (>=3.1.2,<4.0.0)
Requires-Dist: Pillow (>=9.1.1,<10.0.0)
Requires-Dist: more-itertools (>=8.13.0,<9.0.0)
Requires-Dist: pandas (>=1.4.2,<2.0.0)
Requires-Dist: pathlib (>=1.0.1,<2.0.0)
Requires-Dist: python-magic-bin (==0.4.14)
Requires-Dist: termcolor (>=1.1.0,<2.0.0)
Requires-Dist: types-termcolor (>=1.1.4,<2.0.0)
Project-URL: Repository, https://github.com/LordAmit/duplicate_image_finder
